concept/__init__.py
concept/_ctfidf.py
concept/_mmr.py
concept/_model.py
concept/_visualization.py
concept-0.2.1.dist-info/LICENSE
concept-0.2.1.dist-info/METADATA
concept-0.2.1.dist-info/WHEEL
concept-0.2.1.dist-info/top_level.txt
concept-0.2.1.dist-info/RECORD
